jokettt/__init__.py
jokettt/board.py
jokettt/consoleplayer.py
jokettt/learnerplayer.py
jokettt/minimaxplayer.py
jokettt/player.py
jokettt/board/__init__.py
jokettt/board/board.py
jokettt/players/__init__.py
jokettt/players/consoleplayer.py
jokettt/players/learnerplayer.py
jokettt/players/minimaxplayer.py
jokettt/players/player.py
jokettt-1.0.0.dist-info/LICENSE
jokettt-1.0.0.dist-info/METADATA
jokettt-1.0.0.dist-info/WHEEL
jokettt-1.0.0.dist-info/top_level.txt
jokettt-1.0.0.dist-info/RECORD
