Metadata-Version: 2.1
Name: jokettt
Version: 1.0.0
Summary: A Tic Tac Toe game developed by joke
Home-page: https://github.com/fpiantini/jokettt
Author: Francesco Piantini
Author-email: francesco.piantini@gmail.com
License: MIT
Download-URL: https://github.com/fpiantini/jokettt/archive/v1.0.0.tar.gz
Platform: UNKNOWN
Classifier: Programming Language :: Python :: 3
Classifier: License :: OSI Approved :: MIT License
Classifier: Operating System :: OS Independent
Classifier: Development Status :: 5 - Production/Stable
Requires-Python: >=3.6
Requires-Dist: numpy
